pydantic_csv/__init__.py
pydantic_csv/basemodel_csv_reader.py
pydantic_csv/basemodel_csv_writer.py
pydantic_csv/exceptions.py
pydantic_csv/header_mapper.py
pydantic_csv/py.typed
pydantic_csv-0.1.0.dist-info/AUTHORS.md
pydantic_csv-0.1.0.dist-info/LICENSE
pydantic_csv-0.1.0.dist-info/METADATA
pydantic_csv-0.1.0.dist-info/WHEEL
pydantic_csv-0.1.0.dist-info/RECORD
