Metadata-Version: 2.1
Name: pydantic-csv
Version: 0.1.0
Summary: convert CSV to pydantic.BaseModel and vice versa
License: LICENSE
Author: Nathan Richard
Author-email: contact@nathanrichard.dev
Requires-Python: >=3.9,<4.0
Classifier: License :: Other/Proprietary License
Classifier: Programming Language :: Python :: 3
Classifier: Programming Language :: Python :: 3.9
Classifier: Programming Language :: Python :: 3.10
Classifier: Programming Language :: Python :: 3.11
Classifier: Programming Language :: Python :: 3.12
Requires-Dist: pre-commit (>=3.7.1,<4.0.0)
Requires-Dist: pydantic (>=2.7.4,<3.0.0)
Requires-Dist: pytest (>=8.2.2,<9.0.0)
